{
  "project_info": {
    "project_number": "677557829420",
    "project_id": "trash-monitoring-app-88131",
    "storage_bucket": "trash-monitoring-app-88131.firebasestorage.app"
  },
  "client": [
    {
      "client_info": {
        "mobilesdk_app_id": "1:677557829420:android:2eef313a096af2c370f689",
        "android_client_info": {
          "package_name": "com.ascoa.app"
        }
      },
      "oauth_client": [
        {
          "client_id": "677557829420-ckmej1rg4iufigts9rq4b7i1ieevma0l.apps.googleusercontent.com",
          "client_type": 1,
          "android_info": {
            "package_name": "com.ascoa.app",
            "certificate_hash": "551671fe14c0b0fbbbae3d7f14f1e9262f097731"
          }
        },
        {
          "client_id": "677557829420-gp8j8k67or2nbkv9f9u310scfe48mb89.apps.googleusercontent.com",
          "client_type": 3
        }
      ],
      "api_key": [
        {
          "current_key": "AIzaSyBES3ugYqnsfFd-EozP0K1Sk-UofX69UAo"
        }
      ],
      "services": {
        "appinvite_service": {
          "other_platform_oauth_client": [
            {
              "client_id": "677557829420-gp8j8k67or2nbkv9f9u310scfe48mb89.apps.googleusercontent.com",
              "client_type": 3
            },
            {
              "client_id": "677557829420-e6svsfhpt6g91ai2c3opeone1hg36hug.apps.googleusercontent.com",
              "client_type": 2,
              "ios_info": {
                "bundle_id": "com.example.ascoaApp"
              }
            }
          ]
        }
      }
    }
  ],
  "configuration_version": "1"
}